{
    "date": "2025-07-07",
    "total_posts": 5,
    "emotion_distribution": {
        "anger": 20.0,
        "joy": 20.0,
        "sad": 20.0,
        "suprise": 20.0,
        "fear": 20.0
    },
    "top_negative_posts": [
        {
            "text": "That documentary was surprisingly inspiring.",
            "emotion": "anger"
        },
        {
            "text": "I'm feeling very anxious about tomorrow.",
            "emotion": "fear"
        }
    ],
    "recommendations": {
        "books": [],
        "articles": []
    }
}